[
  {
    "video_name": "ted_happier.mp4",
    "local_video_path": "data/raw/ted_happier.mp4",
    "source_platform": "youtube",
    "source_url": "https://www.youtube.com/watch?v=pdRWeK9f02w&t=16s",
    "title": "1 Thing You Can Do Today to Be Happier | Sonja Lyubomirsky | TED",
    "description": "Talk about happiness, relationships, and human connection.",
    "thumbnail_url": "",
    "tags": [
      "talk",
      "happiness",
      "relationships"
    ],
    "created_at": "2026-03-20T00:00:00",
    "ingested_at": "2026-03-20T00:00:00"
  },
  {
    "video_name": "egg.mp4",
    "local_video_path": "data/raw/egg.mp4",
    "source_platform": "local",
    "source_url": "",
    "title": "egg",
    "description": "",
    "thumbnail_url": "",
    "tags": [],
    "created_at": "2026-04-04T23:47:12",
    "ingested_at": "2026-04-04T23:47:12",
    "ingest_method": "local_file",
    "has_audio": true,
    "video_type": "tutorial",
    "estimated_content_style": "action",
    "recommended_search_mode": "Action mode",
    "duration_sec": 326.055
  },
  {
    "video_name": "powfu_death_bed_coffee_for_your_head_official_video_ft_beabadoobee_jJPMnTXl63E.mp4",
    "local_video_path": "data/raw/powfu_death_bed_coffee_for_your_head_official_video_ft_beabadoobee_jJPMnTXl63E.mp4",
    "source_platform": "youtube",
    "source_url": "https://www.youtube.com/watch?v=jJPMnTXl63E",
    "title": "Powfu - death bed (coffee for your head) (Official Video) ft. beabadoobee",
    "description": "Official Video for \"death bed (coffee for your head) \" by Powfu ft. beabadoobee\n\nListen to Powfu: https://Powfu.lnk.to/ListenID\n\nWatch more videos by Powfu: https://Powfu.lnk.to/ListenID/youtube\nSubscribe on YouTube: https://Powfu.lnk.to/subscribeID\n\nFollow Powfu: \nhttps://Powfu.lnk.to/followII\nhttps://Powfu.lnk.to/followWI\nhttps://Powfu.lnk.to/followTI\nhttps://Powfu.lnk.to/followFI\nhttps://Powfu.lnk.to/followWI\n\n#Powfu #deathbed #deathbedcoffeeforyourhead #beabadoobee #Deathbed #Coffeeforyourhead \n\n\nLyrics:\nDon't stay awake for too long\nDon't go to bed\nI'll make a cup of coffee for your head\nI'll get you up and going out of bed\nYeah, I don't wanna fall asleep\nI don't wanna pass away\nI've been thinking of our future 'Cause I'll never see those days\nI don't know why this has happened, but I probably deserve it\nI tried to do my best, but you know that I'm not perfect\nI've been praying for forgiveness, you've been praying for my health\nWhen I leave this earth, hoping you'll find someone else\n'Cause, yeah, we're still young, there's so much we haven't done\nGetting married, start a family, watch your husband with his son\nI wish it could be me, but I won't make it off this bed\nI hope I go to heaven, so I see you once again\nMy life was kinda short, but I got so many blessings\nHappy you were mine, it sucks that it's all ending\nDon't stay awake for too long\nDon't go to bed\nI'll make a cup of coffee for your head\nI'll get you up and going out of bed, yeah\nAnd I, don't stay awake for too long\nDon't go to bed\nI'll make a cup of coffee for your head\nI'll get you up and going out of bed\nYeah, I'm happy that you're here with me\nI'm sorry if I tear up\nWhen me and you were younger, you would always make me cheer up\nTaking goofy videos while walking through the park\nYou would jump into my arms every time you heard a bark\nCuddle in your sheets, sang me sound asleep\nAnd sneak out through your kitchen at exactly 1:03\nSundays went to church, on Mondays watched a movie\nSoon you'll be alone, sorry that you have to lose me\nDon't stay awake for too long\nDon't go to bed\nI'll make a cup of coffee for your head\nI'll get you up and going out of bed\nAnd I, don't stay awake for too long\nDon't go to bed\nI'll make a cup of coffee for your head\nI'll get you up and going out of bed\nDon't stay awake for too long\nDon't go to bed\nI'll make a cup of coffee for your head\nI'll get you up and going out of bed\nAnd I, don't stay awake for too long\nDon't go to bed\nI'll make a cup of coffee for your head\nI'll get you up and going out of bed\nAnd I, don't stay awake for too long\nDon't go to bed\nI'll make a cup of coffee for your head\nI'll get you up and going out of bed\n\nDirector: bedroom (@bedroom.projects)\nProduction Company: COMPULSORY (@compulsoryview)\nExec. Producer: Kiran Mandla (@kir.m_)\nProducer: Joseph J Goldman (@thewarthog)\nProducer/Commissioner: Saul Levitz\n\nProduction Service Co: BOLDLY (@filmboldly)\nProducer: Sebastien Galina (@sebastiengalina)\nDOP: Kaayla Whachell (@kaayla_whachell)\nDOP: Meliodic (@meliodic)\n1st AC: Thomas Wang (@wangerthomas)\nGaffer: Brandon Y Lee (@brandon_y_lee)\nKey Grip: Tom Armstrong (@armstronggrip93)\nGear: Primary Imaging (@primaryimaging)\nColourist: Thomas Mangham (@thomasmangham) @ The Mill",
    "thumbnail_url": "https://i.ytimg.com/vi/jJPMnTXl63E/maxresdefault.jpg",
    "tags": [
      "Powfu",
      "Viral Song",
      "TikTok",
      "DeathBed",
      "Death Bed",
      "Coffee For Your Head",
      "Coffee",
      "Powfu Death Bed",
      "Beabadoobee",
      "Powfu TikTok",
      "Viral Music",
      "Official Video",
      "Don't Stay Away for Too Long",
      "Low-Fi",
      "Indie Alternative"
    ],
    "created_at": "2026-04-04T23:54:49",
    "ingested_at": "2026-04-06T00:03:14",
    "ingest_method": "youtube_url",
    "has_audio": true,
    "video_type": "tutorial",
    "estimated_content_style": "action",
    "recommended_search_mode": "Action mode",
    "duration_sec": 174
  },
  {
    "video_name": "demo.mp4",
    "local_video_path": "C:/Users/Admin/AppData/Local/Temp/pytest-of-Admin/pytest-60/test_process_video_returns_exp0/demo.mp4",
    "source_platform": "local",
    "source_url": "",
    "title": "demo",
    "description": "",
    "thumbnail_url": "",
    "tags": [],
    "ingest_method": "local_file",
    "has_audio": false,
    "video_type": "generic",
    "estimated_content_style": "generic",
    "recommended_search_mode": "Manual",
    "duration_sec": null,
    "created_at": "2026-04-05T09:50:29"
  },
  {
    "video_name": "demo_no_audio.mp4",
    "local_video_path": "C:/Users/Admin/AppData/Local/Temp/pytest-of-Admin/pytest-60/test_process_video_visual_only0/demo_no_audio.mp4",
    "source_platform": "local",
    "source_url": "",
    "title": "demo_no_audio",
    "description": "",
    "thumbnail_url": "",
    "tags": [],
    "ingest_method": "local_file",
    "has_audio": false,
    "video_type": "generic",
    "estimated_content_style": "generic",
    "recommended_search_mode": "Manual",
    "duration_sec": null,
    "created_at": "2026-04-05T09:50:29"
  },
  {
    "video_name": "days_of_summer_m0FYJ3s67hg.mp4",
    "local_video_path": "data/raw/days_of_summer_m0FYJ3s67hg.mp4",
    "source_platform": "youtube",
    "source_url": "https://www.youtube.com/watch?v=m0FYJ3s67hg",
    "title": "Days Of Summer",
    "description": "Filmed over the last few weeks of summer, in no particular order.\n\n\nThank you to Jorden for always being down to explore small towns, camp in the wilderness and film this entire project with me. ♡ Check him out here!\n➫ Insta: https://www.instagram.com/byjorden\n➫ Vimeo: https://www.vimeo.com/jordenlee\n\nFind me here:\n➫ Instagram: https://www.instagram.com/lifeofriza/\n➫ Twitter: https://www.twitter.com/lifeofriza\n➫ Tiktok: https://vm.tiktok.com/ZMeK22VsH\n➫ Business Inquires: hello@lifeofriza.com\n\nGear I Use:\nFave Camera - https://amzn.to/3KlyHgB\nVlogging Lens - https://amzn.to/3DxD6cD\nCINEMATIC Lens - https://amzn.to/4576KBi\nVariable ND - https://amzn.to/43I70Fv\nProMist https://amzn.to/44Tprso\nBEST Lav Mic - https://amzn.to/43PrxYV\nVlogging Mic - https://amzn.to/457Qq3g\nStudio Mic - https://amzn.to/3Klwy4C\nMotorized Slider - https://amzn.to/3YbQEnw\nTripod - https://amzn.to/3OxTJey\n\nLife Of Riza is a participant in the Amazon Services LLC Associates Program, an affiliate advertising program designed to provide a means for sites to earn advertising fees by advertising and linking to Amazon.com \n\nThe music I use in my videos! 30 day free trial: https://www.musicbed.com/invite/WSV9f\n\nDon't forget to subscribe and like this video :) thank you for your support!",
    "thumbnail_url": "https://i.ytimg.com/vi/m0FYJ3s67hg/maxresdefault.jpg",
    "tags": [
      "days of summer",
      "scenes of summer",
      "scenes from summer will darbyshire",
      "life of riza",
      "lifeofriza",
      "kariza santos",
      "kariza",
      "summer cinematic short film",
      "finding summer",
      "short film sony a7s iii"
    ],
    "created_at": "2026-04-05T10:43:40",
    "ingested_at": "2026-04-05T10:43:40",
    "ingest_method": "youtube_url",
    "has_audio": true,
    "video_type": "cinematic",
    "estimated_content_style": "cinematic_music",
    "recommended_search_mode": "Visual mode",
    "duration_sec": 198
  }
]